logstash_utils/CameraLogService.py
logstash_utils/LogService.py
logstash_utils/__init__.py
log_util_huynhnt-1.1.0.dist-info/LICENSE
log_util_huynhnt-1.1.0.dist-info/METADATA
log_util_huynhnt-1.1.0.dist-info/WHEEL
log_util_huynhnt-1.1.0.dist-info/top_level.txt
log_util_huynhnt-1.1.0.dist-info/RECORD
