Metadata-Version: 2.1
Name: log-util-huynhnt
Version: 1.1.0
Summary: Logging with logstash
Home-page: https://gitlab.com/fiop/hcc/camera-system/log-util
Author: Nguyen Thuc Huynh
Author-email: huynhnt6995@gmail.com
License: UNKNOWN
Platform: UNKNOWN
Classifier: Programming Language :: Python :: 3
Classifier: License :: OSI Approved :: MIT License
Classifier: Operating System :: OS Independent
Requires-Python: >=3.6
Requires-Dist: python-dotenv
Requires-Dist: python3-logstash
